kubernetes/__init__.py
kubernetes/client/__init__.py
kubernetes/client/api_client.py
kubernetes/client/configuration.py
kubernetes/client/rest.py
kubernetes/client/ws_client.py
kubernetes/client/apis/__init__.py
kubernetes/client/apis/apis_api.py
kubernetes/client/apis/apps_api.py
kubernetes/client/apis/apps_v1beta1_api.py
kubernetes/client/apis/authentication_api.py
kubernetes/client/apis/authentication_v1beta1_api.py
kubernetes/client/apis/autoscaling_api.py
kubernetes/client/apis/autoscaling_v1_api.py
kubernetes/client/apis/batch_api.py
kubernetes/client/apis/batch_v1_api.py
kubernetes/client/apis/batch_v2alpha1_api.py
kubernetes/client/apis/certificates_api.py
kubernetes/client/apis/certificates_v1alpha1_api.py
kubernetes/client/apis/core_api.py
kubernetes/client/apis/core_v1_api.py
kubernetes/client/apis/default_api.py
kubernetes/client/apis/extensions_api.py
kubernetes/client/apis/extensions_v1beta1_api.py
kubernetes/client/apis/oapi_api.py
kubernetes/client/apis/osapi_api.py
kubernetes/client/apis/policy_api.py
kubernetes/client/apis/policy_v1beta1_api.py
kubernetes/client/apis/storage_api.py
kubernetes/client/apis/storage_v1beta1_api.py
kubernetes/client/apis/third_party_resources_api.py
kubernetes/client/apis/version_api.py
kubernetes/client/models/__init__.py
kubernetes/client/models/runtime_raw_extension.py
kubernetes/client/models/unversioned_api_group.py
kubernetes/client/models/unversioned_api_group_list.py
kubernetes/client/models/unversioned_api_resource.py
kubernetes/client/models/unversioned_api_resource_list.py
kubernetes/client/models/unversioned_api_versions.py
kubernetes/client/models/unversioned_group_version_for_discovery.py
kubernetes/client/models/unversioned_label_selector.py
kubernetes/client/models/unversioned_label_selector_requirement.py
kubernetes/client/models/unversioned_list_meta.py
kubernetes/client/models/unversioned_server_address_by_client_cidr.py
openshift_client_python-2.0.0.dist-info/DESCRIPTION.rst
openshift_client_python-2.0.0.dist-info/METADATA
openshift_client_python-2.0.0.dist-info/RECORD
openshift_client_python-2.0.0.dist-info/WHEEL
openshift_client_python-2.0.0.dist-info/metadata.json
openshift_client_python-2.0.0.dist-info/top_level.txt
