Metadata-Version: 2.0
Name: openshift-client-python
Version: 2.0.0
Summary: Openshift python client
Home-page: https://github.com/caruccio/client-python
Author: Kubernetes
Author-email: UNKNOWN
License: Apache License Version 2.0
Keywords: Swagger,OpenAPI,Kubernetes,Openshift
Platform: UNKNOWN
Classifier: Development Status :: 3 - Alpha
Classifier: Topic :: Utilities
Classifier: Intended Audience :: Developers
Classifier: Intended Audience :: Information Technology
Classifier: License :: OSI Approved :: Apache Software License
Classifier: Operating System :: OS Independent
Classifier: Programming Language :: Python
Classifier: Programming Language :: Python :: 2
Classifier: Programming Language :: Python :: 2.7
Classifier: Programming Language :: Python :: 3
Classifier: Programming Language :: Python :: 3.4
Classifier: Programming Language :: Python :: 3.5
Requires-Dist: certifi (>=14.05.14)
Requires-Dist: ipaddress (>=1.0.17)
Requires-Dist: oauth2client (>=4.0.0)
Requires-Dist: python-dateutil (>=2.5.3)
Requires-Dist: pyyaml (>=3.12)
Requires-Dist: setuptools (>=21.0.0)
Requires-Dist: six (>=1.9.0)
Requires-Dist: urllib3 (!=1.21,>=1.19.1)
Requires-Dist: websocket-client (>=0.32.0)
